__init__.py
models/Listing.py
models/ListingImage.py
models/ListingProperty.py
models/Price.py
models/ProductionPartner.py
models/Receipt.py
models/Review.py
models/Shipment.py
models/ShippingProfile.py
models/ShippingProfileDestination.py
models/ShippingProfileUpgrade.py
models/Shop.py
models/Transaction.py
models/Translation.py
models/User.py
models/Variation.py
models/__init__.py
resources/ListingResource.py
resources/ReceiptResource.py
resources/ReviewResource.py
resources/ShopResource.py
resources/TransactionResource.py
resources/__init__.py
utils/APIV3.py
utils/RequestException.py
utils/Response.py
utils/__init__.py
etsy_apiv3_sdk_2-1.0.2.dist-info/METADATA
etsy_apiv3_sdk_2-1.0.2.dist-info/WHEEL
etsy_apiv3_sdk_2-1.0.2.dist-info/top_level.txt
etsy_apiv3_sdk_2-1.0.2.dist-info/RECORD
